eegdash/__init__.py
eegdash/api.py
eegdash/bids_metadata.py
eegdash/const.py
eegdash/downloader.py
eegdash/http_api_client.py
eegdash/local_bids.py
eegdash/logging.py
eegdash/paths.py
eegdash/schemas.py
eegdash/dataset/__init__.py
eegdash/dataset/base.py
eegdash/dataset/bids_dataset.py
eegdash/dataset/dataset.py
eegdash/dataset/dataset_summary.csv
eegdash/dataset/registry.py
eegdash/features/__init__.py
eegdash/features/datasets.py
eegdash/features/decorators.py
eegdash/features/extractors.py
eegdash/features/inspect.py
eegdash/features/serialization.py
eegdash/features/utils.py
eegdash/features/feature_bank/__init__.py
eegdash/features/feature_bank/complexity.py
eegdash/features/feature_bank/connectivity.py
eegdash/features/feature_bank/csp.py
eegdash/features/feature_bank/dimensionality.py
eegdash/features/feature_bank/signal.py
eegdash/features/feature_bank/spectral.py
eegdash/features/feature_bank/utils.py
eegdash/hbn/__init__.py
eegdash/hbn/preprocessing.py
eegdash/hbn/windows.py
eegdash-0.5.0.dist-info/licenses/LICENSE
eegdash-0.5.0.dist-info/METADATA
eegdash-0.5.0.dist-info/WHEEL
eegdash-0.5.0.dist-info/top_level.txt
eegdash-0.5.0.dist-info/RECORD
