Metadata-Version: 2.4
Name: eegdash
Version: 0.5.0
Summary: EEG data for machine learning
Author-email: Young Truong <dt.young112@gmail.com>, Arnaud Delorme <adelorme@ucsd.edu>, Aviv Dotan <avivdot@bgu.post.ac.il>, Oren Shriki <shrikio@bgu.ac.il>, Bruno Aristimunha <b.aristimunha@gmail.com>
License-Expression: BSD-3-Clause
Project-URL: Homepage, https://github.com/sccn/EEG-Dash-Data
Project-URL: Issues, https://github.com/sccn/EEG-Dash-Data/issues
Classifier: Operating System :: OS Independent
Classifier: Intended Audience :: Science/Research
Classifier: Intended Audience :: Developers
Classifier: Programming Language :: Python
Classifier: Topic :: Software Development
Classifier: Topic :: Scientific/Engineering
Classifier: Development Status :: 3 - Alpha
Classifier: Operating System :: Microsoft :: Windows
Classifier: Operating System :: POSIX
Classifier: Operating System :: Unix
Classifier: Operating System :: MacOS
Classifier: Programming Language :: Python :: 3
Classifier: Programming Language :: Python :: 3.10
Classifier: Programming Language :: Python :: 3.11
Classifier: Programming Language :: Python :: 3.12
Classifier: Programming Language :: Python :: 3.13
Requires-Python: >=3.11
License-File: LICENSE
Requires-Dist: braindecode[hub]>=1.3.2
Requires-Dist: mne_bids>=0.18.0
Requires-Dist: numba
Requires-Dist: requests>=2.25.0
Requires-Dist: s3fs
Requires-Dist: tqdm
Requires-Dist: pymatreader
Requires-Dist: eeglabio
Requires-Dist: tabulate
Requires-Dist: rich
Requires-Dist: pyarrow
Requires-Dist: pandas>=2.0
Requires-Dist: pydantic
Provides-Extra: tests
Requires-Dist: pytest; extra == "tests"
Requires-Dist: pytest-cov; extra == "tests"
Requires-Dist: pytest-sugar; extra == "tests"
Requires-Dist: codecov; extra == "tests"
Requires-Dist: pytest_cases; extra == "tests"
Requires-Dist: pytest-benchmark; extra == "tests"
Requires-Dist: pytest-xdist; extra == "tests"
Provides-Extra: dev
Requires-Dist: pre-commit; extra == "dev"
Requires-Dist: ipykernel; extra == "dev"
Requires-Dist: lightning>=2.0; extra == "dev"
Requires-Dist: torchmetrics>=0.7; extra == "dev"
Requires-Dist: scikit-learn; extra == "dev"
Requires-Dist: tensorboard; extra == "dev"
Provides-Extra: docs
Requires-Dist: sphinx; extra == "docs"
Requires-Dist: sphinx_design; extra == "docs"
Requires-Dist: sphinx_gallery; extra == "docs"
Requires-Dist: sphinx_rtd_theme; extra == "docs"
Requires-Dist: pydata-sphinx-theme; extra == "docs"
Requires-Dist: sphinx-autobuild; extra == "docs"
Requires-Dist: sphinx-copybutton; extra == "docs"
Requires-Dist: sphinx-sitemap; extra == "docs"
Requires-Dist: numpydoc; extra == "docs"
Requires-Dist: memory_profiler; extra == "docs"
Requires-Dist: ipython; extra == "docs"
Requires-Dist: lightgbm; extra == "docs"
Requires-Dist: plotly; extra == "docs"
Requires-Dist: nbformat; extra == "docs"
Requires-Dist: graphviz; extra == "docs"
Requires-Dist: neato; extra == "docs"
Requires-Dist: moabb; extra == "docs"
Provides-Extra: digestion
Requires-Dist: pybids; extra == "digestion"
Requires-Dist: gql[requests]; extra == "digestion"
Requires-Dist: requests_toolbelt; extra == "digestion"
Requires-Dist: beautifulsoup4; extra == "digestion"
Requires-Dist: python-dotenv; extra == "digestion"
Requires-Dist: selenium; extra == "digestion"
Requires-Dist: httpx; extra == "digestion"
Requires-Dist: tenacity; extra == "digestion"
Requires-Dist: hishel; extra == "digestion"
Requires-Dist: pydantic>=2; extra == "digestion"
Requires-Dist: PyGithub>=2; extra == "digestion"
Provides-Extra: all
Requires-Dist: eegdash[docs]; extra == "all"
Requires-Dist: eegdash[dev]; extra == "all"
Requires-Dist: eegdash[tests]; extra == "all"
Requires-Dist: eegdash[digestion]; extra == "all"
Dynamic: license-file
